oemof_tabular_plugins/__init__.py
oemof_tabular_plugins/_version.py
oemof_tabular_plugins/general/__init__.py
oemof_tabular_plugins/general/constraint_facades.py
oemof_tabular_plugins/general/constraints.py
oemof_tabular_plugins/general/post_processing.py
oemof_tabular_plugins/general/pre_processing.py
oemof_tabular_plugins/hydrogen/__init__.py
oemof_tabular_plugins/hydrogen/constraint_facades.py
oemof_tabular_plugins/hydrogen/constraints.py
oemof_tabular_plugins/hydrogen/post_processing.py
oemof_tabular_plugins/wefe/__init__.py
oemof_tabular_plugins/wefe/constraint_facades.py
oemof_tabular_plugins/wefe/constraints.py
oemof_tabular_plugins/wefe/post_processing.py
oemof_tabular_plugins/wefe/facades/__init__.py
oemof_tabular_plugins/wefe/facades/pv_panel.py
oemof_tabular_plugins-0.0.1.dist-info/LICENSE.txt
oemof_tabular_plugins-0.0.1.dist-info/METADATA
oemof_tabular_plugins-0.0.1.dist-info/WHEEL
oemof_tabular_plugins-0.0.1.dist-info/entry_points.txt
oemof_tabular_plugins-0.0.1.dist-info/top_level.txt
oemof_tabular_plugins-0.0.1.dist-info/RECORD
