Metadata-Version: 2.1
Name: oemof-tabular-plugins
Version: 0.0.1
Summary: A package that contains various constraint facades to be used with oemof-tabular
Author-email: Ciara Dunks <ciara.dunks@rl-institut.de>, Pierre-François Duc <pierre-francois.duc@rl-institut.de>
Project-URL: Homepage, https://github.com/rl-institut/oemof-tabular-plugins
Project-URL: Issues, https://github.com/rl-institut/oemof-tabular-plugins/issues
Classifier: Programming Language :: Python :: 3
Classifier: License :: OSI Approved :: MIT License
Classifier: Operating System :: OS Independent
Requires-Python: >=3.9
License-File: LICENSE.txt
Requires-Dist: oemof-tabular
